podarr/__init__.py
podarr/__main__.py
podarr/api/__init__.py
podarr/api/endpoints.py
podarr/database/__init__.py
podarr/database/base.py
podarr/database/models.py
podarr/library/__init__.py
podarr/library/basher.py
podarr/library/directories.py
podarr/library/notifications.py
podarr/library/podman.py
podarr/library/system_info.py
podarr/library/systemd.py
podarr/services/__init__.py
podarr/services/autobackup.py
podarr/services/autoupload.py
podarr/services/backend.py
podarr/services/base.py
podarr/services/bazarr.py
podarr/services/frontend.py
podarr/services/lidarr.py
podarr/services/mergerfs.py
podarr/services/plex.py
podarr/services/prowlarr.py
podarr/services/qbittorrent.py
podarr/services/radarr.py
podarr/services/rclone.py
podarr/services/sabnzbd.py
podarr/services/sonarr.py
podarr-1.0.8.dist-info/LICENSE
podarr-1.0.8.dist-info/METADATA
podarr-1.0.8.dist-info/WHEEL
podarr-1.0.8.dist-info/entry_points.txt
podarr-1.0.8.dist-info/top_level.txt
podarr-1.0.8.dist-info/RECORD
