Metadata-Version: 2.1
Name: podarr
Version: 1.0.8
Summary: Python manager for Arr and Plex services
Author: podarr
Author-email: podarr@proton.me
License: GPL
Project-URL: Source, https://github.com/podman-arr/podarr-cli
Project-URL: Documentation, https://github.com/podman-arr/podarr-cli
Requires-Python: >=3.8
License-File: LICENSE
Requires-Dist: inquirer
Requires-Dist: fastapi
Requires-Dist: uvicorn
Requires-Dist: configobj
Requires-Dist: SQLAlchemy
Requires-Dist: pydantic
Requires-Dist: psutil
Requires-Dist: requests
Requires-Dist: fastapi-utils
